napari_segmentation_toolbox/__init__.py
napari_segmentation_toolbox/_version.py
napari_segmentation_toolbox/layer_controls.py
napari_segmentation_toolbox/main_widget.py
napari_segmentation_toolbox/napari.yaml
napari_segmentation_toolbox/plane_slider_widget.py
napari_segmentation_toolbox/plot_widget.py
napari_segmentation_toolbox/regionprops_widget.py
napari_segmentation_toolbox/toolwidgets.py
napari_segmentation_toolbox/_tests/__init__.py
napari_segmentation_toolbox/_tests/conftest.py
napari_segmentation_toolbox/_tests/test2d.tif
napari_segmentation_toolbox/_tests/test3d.tif
napari_segmentation_toolbox/_tests/test4d.tif
napari_segmentation_toolbox/_tests/test_action_functions.py
napari_segmentation_toolbox/_tests/test_actions.py
napari_segmentation_toolbox/_tests/test_copy_label.py
napari_segmentation_toolbox/_tests/test_custom_table.py
napari_segmentation_toolbox/_tests/test_layer_control_widgets.py
napari_segmentation_toolbox/_tests/test_measure_regionprops.py
napari_segmentation_toolbox/_tests/test_regionprop_widget.py
napari_segmentation_toolbox/_tests/test_select_delete_by_mask.py
napari_segmentation_toolbox/helpers/__init__.py
napari_segmentation_toolbox/helpers/base_tool_widget.py
napari_segmentation_toolbox/helpers/layer_dropdown.py
napari_segmentation_toolbox/helpers/process_actions_helpers.py
napari_segmentation_toolbox/icons/Back.png
napari_segmentation_toolbox/icons/Forward.png
napari_segmentation_toolbox/icons/Home.png
napari_segmentation_toolbox/icons/Pan.png
napari_segmentation_toolbox/icons/Pan_checked.png
napari_segmentation_toolbox/icons/Zoom.png
napari_segmentation_toolbox/icons/Zoom_checked.png
napari_segmentation_toolbox/icons/configure_subplots.png
napari_segmentation_toolbox/icons/edit_parameters.png
napari_segmentation_toolbox/icons/save_figure.png
napari_segmentation_toolbox/layer_control_widgets/__init__.py
napari_segmentation_toolbox/layer_control_widgets/convert_to_numpy.py
napari_segmentation_toolbox-0.0.4.dist-info/licenses/LICENSE
napari_segmentation_toolbox-0.0.4.dist-info/METADATA
napari_segmentation_toolbox-0.0.4.dist-info/WHEEL
napari_segmentation_toolbox-0.0.4.dist-info/entry_points.txt
napari_segmentation_toolbox-0.0.4.dist-info/top_level.txt
napari_segmentation_toolbox-0.0.4.dist-info/RECORD
