Metadata-Version: 2.4
Name: napari-segmentation-toolbox
Version: 0.0.4
Summary: Toolbox for viewing, analyzing, and manually correcting (cell) segmentation in napari.
Author-email: Anniek Stokkermans <anniek.stokkermans@gmail.com>
License: 
Project-URL: Homepage, https://github.com/AnniekStok/napari-segmentation-toolbox
Project-URL: Issues, https://github.com/AnniekStok/napari-segmentation-toolbox/issues
Classifier: Development Status :: 2 - Pre-Alpha
Classifier: Framework :: napari
Classifier: Intended Audience :: Developers
Classifier: License :: OSI Approved :: BSD License
Classifier: Operating System :: OS Independent
Classifier: Programming Language :: Python
Classifier: Programming Language :: Python :: 3
Classifier: Programming Language :: Python :: 3 :: Only
Classifier: Programming Language :: Python :: 3.10
Classifier: Programming Language :: Python :: 3.11
Classifier: Programming Language :: Python :: 3.12
Classifier: Programming Language :: Python :: 3.13
Classifier: Topic :: Scientific/Engineering :: Image Processing
Requires-Python: >=3.10
License-File: LICENSE
Requires-Dist: napari>=0.6.2
Requires-Dist: numpy<2.0
Requires-Dist: scipy<1.12
Requires-Dist: scikit-image<0.26,>=0.24.0
Requires-Dist: dask[array]<=2025
Requires-Dist: dask_image<=2025
Requires-Dist: matplotlib<3.9
Requires-Dist: napari-orthogonal-views>=0.0.7
Provides-Extra: all
Requires-Dist: napari[all]; extra == "all"
Provides-Extra: testing
Requires-Dist: tox; extra == "testing"
Requires-Dist: pytest; extra == "testing"
Requires-Dist: pytest-cov; extra == "testing"
Requires-Dist: pytest-qt; extra == "testing"
Requires-Dist: napari[qt]; extra == "testing"
Dynamic: license-file
